{
    "face": {
        "predictions": [
            {
                "frame": 0,
                "time": null,
                "bbox": {
                    "x": 197.00775146484375,
                    "y": 160.7535400390625,
                    "w": 127.52081298828125,
                    "h": 158.864013671875
                },
                "prob": 0.9998979568481445,
                "face_id": "face_0",
                "emotions": [
                    {
                        "name": "Admiration",
                        "score": 0.06922361999750137
                    },
                    {
                        "name": "Adoration",
                        "score": 0.04988545924425125
                    },
                    {
                        "name": "Aesthetic Appreciation",
                        "score": 0.06095590069890022
                    },
                    {
                        "name": "Amusement",
                        "score": 0.09242253005504608
                    },
                    {
                        "name": "Anger",
                        "score": 0.09808572381734848
                    },
                    {
                        "name": "Anxiety",
                        "score": 0.1371045559644699
                    },
                    {
                        "name": "Awe",
                        "score": 0.044139403849840164
                    },
                    {
                        "name": "Awkwardness",
                        "score": 0.22466875612735748
                    },
                    {
                        "name": "Boredom",
                        "score": 0.6433501243591309
                    },
                    {
                        "name": "Calmness",
                        "score": 0.6058899760246277
                    },
                    {
                        "name": "Concentration",
                        "score": 0.5177690386772156
                    },
                    {
                        "name": "Contemplation",
                        "score": 0.22200524806976318
                    },
                    {
                        "name": "Confusion",
                        "score": 0.32862821221351624
                    },
                    {
                        "name": "Contempt",
                        "score": 0.23992253839969635
                    },
                    {
                        "name": "Contentment",
                        "score": 0.13629375398159027
                    },
                    {
                        "name": "Craving",
                        "score": 0.05158301442861557
                    },
                    {
                        "name": "Determination",
                        "score": 0.14662063121795654
                    },
                    {
                        "name": "Disappointment",
                        "score": 0.3832409381866455
                    },
                    {
                        "name": "Disgust",
                        "score": 0.1065606102347374
                    },
                    {
                        "name": "Distress",
                        "score": 0.1676643043756485
                    },
                    {
                        "name": "Doubt",
                        "score": 0.32162603735923767
                    },
                    {
                        "name": "Ecstasy",
                        "score": 0.019418073818087578
                    },
                    {
                        "name": "Embarrassment",
                        "score": 0.09194526076316833
                    },
                    {
                        "name": "Empathic Pain",
                        "score": 0.085757777094841
                    },
                    {
                        "name": "Entrancement",
                        "score": 0.10937532782554626
                    },
                    {
                        "name": "Envy",
                        "score": 0.053516991436481476
                    },
                    {
                        "name": "Excitement",
                        "score": 0.033205028623342514
                    },
                    {
                        "name": "Fear",
                        "score": 0.05457039549946785
                    },
                    {
                        "name": "Guilt",
                        "score": 0.08638713508844376
                    },
                    {
                        "name": "Horror",
                        "score": 0.020071959123015404
                    },
                    {
                        "name": "Interest",
                        "score": 0.2642582058906555
                    },
                    {
                        "name": "Joy",
                        "score": 0.058079615235328674
                    },
                    {
                        "name": "Love",
                        "score": 0.06208684667944908
                    },
                    {
                        "name": "Nostalgia",
                        "score": 0.0685867890715599
                    },
                    {
                        "name": "Pain",
                        "score": 0.1022750586271286
                    },
                    {
                        "name": "Pride",
                        "score": 0.07236263155937195
                    },
                    {
                        "name": "Realization",
                        "score": 0.11878710240125656
                    },
                    {
                        "name": "Relief",
                        "score": 0.05849406123161316
                    },
                    {
                        "name": "Romance",
                        "score": 0.03332022950053215
                    },
                    {
                        "name": "Sadness",
                        "score": 0.2829844653606415
                    },
                    {
                        "name": "Satisfaction",
                        "score": 0.10297632962465286
                    },
                    {
                        "name": "Desire",
                        "score": 0.04633500427007675
                    },
                    {
                        "name": "Shame",
                        "score": 0.08306191861629486
                    },
                    {
                        "name": "Surprise (negative)",
                        "score": 0.02827310748398304
                    },
                    {
                        "name": "Surprise (positive)",
                        "score": 0.017657384276390076
                    },
                    {
                        "name": "Sympathy",
                        "score": 0.07549527287483215
                    },
                    {
                        "name": "Tiredness",
                        "score": 0.3121390640735626
                    },
                    {
                        "name": "Triumph",
                        "score": 0.023378534242510796
                    }
                ]
            }
        ]
    }
}